cronus_eater/__init__.py
cronus_eater/__main__.py
cronus_eater/_converter.py
cronus_eater/_extractor.py
cronus_eater/_normalizer.py
cronus_eater/_validator.py
cronus_eater/exceptions.py
cronus_eater/model.py
cronus_eater-0.1.0a10.dist-info/LICENSE
cronus_eater-0.1.0a10.dist-info/METADATA
cronus_eater-0.1.0a10.dist-info/WHEEL
cronus_eater-0.1.0a10.dist-info/entry_points.txt
cronus_eater-0.1.0a10.dist-info/RECORD
