Metadata-Version: 2.1
Name: cronus-eater
Version: 0.1.0a10
Summary: A simple tool to get time series from spreadsheets
Home-page: https://github.com/breno-jesus-fernandes/cronus-eater
License: MIT
Keywords: time series,historical series,chronological data sequence,extract,normalize,spreadsheet
Author: Breno Fernandes
Author-email: breno.de.jesus.fernandes@gmail.com
Requires-Python: >=3.7.1,<3.12
Classifier: Development Status :: 2 - Pre-Alpha
Classifier: Intended Audience :: Developers
Classifier: Intended Audience :: Financial and Insurance Industry
Classifier: Intended Audience :: Information Technology
Classifier: Intended Audience :: Science/Research
Classifier: License :: OSI Approved :: MIT License
Classifier: Operating System :: OS Independent
Classifier: Programming Language :: Python
Classifier: Programming Language :: Python :: 3
Classifier: Programming Language :: Python :: 3.8
Classifier: Programming Language :: Python :: 3.9
Classifier: Programming Language :: Python :: 3.10
Classifier: Programming Language :: Python :: 3.11
Classifier: Programming Language :: Python :: 3
Classifier: Programming Language :: Python :: 3 :: Only
Classifier: Programming Language :: Python :: 3.10
Classifier: Programming Language :: Python :: 3.11
Classifier: Programming Language :: Python :: 3.7
Classifier: Programming Language :: Python :: 3.8
Classifier: Programming Language :: Python :: 3.9
Classifier: Typing :: Typed
Requires-Dist: loguru (>=0.6.0,<0.7.0)
Requires-Dist: openpyxl (>=3.0.10,<4.0.0)
Requires-Dist: pandas (==1.3.5) ; python_full_version >= "3.7.1" and python_version < "3.8"
Requires-Dist: pandas (>=1.5.0,<2.0.0) ; python_version >= "3.8" and python_version < "3.12"
Requires-Dist: typing-extensions (>=4.5.0,<5.0.0)
Requires-Dist: unidecode (>=1.3.6,<2.0.0)
Project-URL: Bug Tracker, https://github.com/breno-jesus-fernandes/cronus-eater/issues
Project-URL: Documentation, https://github.com/breno-jesus-fernandes/cronus-eater/docs
Project-URL: Repository, https://github.com/breno-jesus-fernandes/cronus-eater
